hatch_build.py
web/wgscovplot.html.j2
web/build/wgscovplot.js
wgscovplot/__about__.py
wgscovplot/__init__.py
wgscovplot/cli.py
wgscovplot/colors.py
wgscovplot/config.py
wgscovplot/db.py
wgscovplot/features.py
wgscovplot/flu.py
wgscovplot/io.py
wgscovplot/rtpcr.py
wgscovplot/util.py
wgscovplot/wgscovplot.py
wgscovplot/tools/__init__.py
wgscovplot/tools/variants.py
wgscovplot/tools/mosdepth/__init__.py
wgscovplot/tools/mosdepth/flu.py
wgscovplot-1.0.2.dist-info/METADATA
wgscovplot-1.0.2.dist-info/WHEEL
wgscovplot-1.0.2.dist-info/entry_points.txt
wgscovplot-1.0.2.dist-info/licenses/LICENSE
wgscovplot-1.0.2.dist-info/RECORD
