Metadata-Version: 2.3
Name: wgscovplot
Version: 1.0.2
Summary: Create interactive comparative sequencing coverage plots from virus sequencing data.
Project-URL: Documentation, https://github.com/CFIA-NCFAD/wgscovplot#readme
Project-URL: Issues, https://github.com/CFIA-NCFAD/wgscovplot/issues
Project-URL: Source, https://github.com/CFIA-NCFAD/wgscovplot
Author-email: Hai Hoang Nguyen <hoanghai.nguyen@inspection.gc.ca>, Peter Kruczkiewicz <peter.kruczkiewicz@gmail.com>
License-Expression: Apache-2.0
License-File: LICENSE
Classifier: Development Status :: 4 - Beta
Classifier: Programming Language :: Python
Classifier: Programming Language :: Python :: 3.9
Classifier: Programming Language :: Python :: 3.10
Classifier: Programming Language :: Python :: 3.11
Classifier: Programming Language :: Python :: Implementation :: CPython
Requires-Python: >=3.9
Requires-Dist: bcbio-gff
Requires-Dist: biopython
Requires-Dist: edlib
Requires-Dist: jinja2
Requires-Dist: pandas
Requires-Dist: pydantic>=2.0.0
Requires-Dist: pysam
Requires-Dist: rich
Requires-Dist: typer
